{
  "project_info": {
    "project_number": "1072362823781",
    "firebase_url": "https://newnode-1876b-default-rtdb.firebaseio.com",
    "project_id": "newnode-1876b",
    "storage_bucket": "newnode-1876b.appspot.com"
  },
  "client": [
    {
      "client_info": {
        "mobilesdk_app_id": "1:1072362823781:android:f16dba1793a99a3e4ea68c",
        "android_client_info": {
          "package_name": "codingwithmitch.com.googlemapsgoogleplaces"
        }
      },
      "oauth_client": [
        {
          "client_id": "1072362823781-mh9kft7gemhrm0cmrg7b8hukchgqm471.apps.googleusercontent.com",
          "client_type": 3
        }
      ],
      "api_key": [
        {
          "current_key": "AIzaSyDa5OVpnbnOUjclvUKoJ4-CMT5N9la19sY"
        }
      ],
      "services": {
        "appinvite_service": {
          "other_platform_oauth_client": [
            {
              "client_id": "1072362823781-mh9kft7gemhrm0cmrg7b8hukchgqm471.apps.googleusercontent.com",
              "client_type": 3
            }
          ]
        }
      }
    },
    {
      "client_info": {
        "mobilesdk_app_id": "1:1072362823781:android:6b6960393809a7f84ea68c",
        "android_client_info": {
          "package_name": "com.example.firebaseconnection"
        }
      },
      "oauth_client": [
        {
          "client_id": "1072362823781-mh9kft7gemhrm0cmrg7b8hukchgqm471.apps.googleusercontent.com",
          "client_type": 3
        }
      ],
      "api_key": [
        {
          "current_key": "AIzaSyDa5OVpnbnOUjclvUKoJ4-CMT5N9la19sY"
        }
      ],
      "services": {
        "appinvite_service": {
          "other_platform_oauth_client": [
            {
              "client_id": "1072362823781-mh9kft7gemhrm0cmrg7b8hukchgqm471.apps.googleusercontent.com",
              "client_type": 3
            }
          ]
        }
      }
    }
  ],
  "configuration_version": "1"
}